LICENSE
MANIFEST.in
setup.cfg
setup.py
alphaui/__init__.py
alphaui/blocks.py
alphaui/component.py
alphaui/components.py
alphaui/context.py
alphaui/deprecation.py
alphaui/documentation.py
alphaui/encryptor.py
alphaui/events.py
alphaui/examples.py
alphaui/external.py
alphaui/flagging.py
alphaui/inputs.py
alphaui/interface.py
alphaui/interpretation.py
alphaui/ipython_ext.py
alphaui/launchable.py
alphaui/layouts.py
alphaui/media_data.py
alphaui/mix.py
alphaui/networking.py
alphaui/outputs.py
alphaui/process_examples.py
alphaui/processing_utils.py
alphaui/queueing.py
alphaui/reload.py
alphaui/routes.py
alphaui/static.py
alphaui/strings.py
alphaui/templates.py
alphaui/test_data.py
alphaui/tunneling.py
alphaui/utils.py
alphaui/version.txt
alphaui.egg-info/PKG-INFO
alphaui.egg-info/SOURCES.txt
alphaui.egg-info/dependency_links.txt
alphaui.egg-info/requires.txt
alphaui.egg-info/top_level.txt
alphaui/templates/api_docs.html
alphaui/templates/cdn/favicon.png
alphaui/templates/cdn/gradio.js
alphaui/templates/cdn/index.html
alphaui/templates/cdn/assets/Block.e9dcd6ee.js
alphaui/templates/cdn/assets/BlockLabel.07858bf7.js
alphaui/templates/cdn/assets/BlockTitle.cd41831f.js
alphaui/templates/cdn/assets/CarouselItem.svelte_svelte_type_style_lang.d5c0383c.js
alphaui/templates/cdn/assets/CarouselItem.svelte_svelte_type_style_lang.d8150608.css
alphaui/templates/cdn/assets/File.ac33c6f7.js
alphaui/templates/cdn/assets/Image.08daf384.js
alphaui/templates/cdn/assets/Image.3aaf495a.js
alphaui/templates/cdn/assets/Model3D.53142d9a.js
alphaui/templates/cdn/assets/ModifyUpload.3af249b2.js
alphaui/templates/cdn/assets/Tabs.ebea5916.js
alphaui/templates/cdn/assets/Upload.c64cec0c.js
alphaui/templates/cdn/assets/Webcam.dda9150b.js
alphaui/templates/cdn/assets/_commonjsHelpers.88e99c8f.js
alphaui/templates/cdn/assets/color.3ab0efd5.js
alphaui/templates/cdn/assets/dsv.7fe76a93.js
alphaui/templates/cdn/assets/index.07b84ca3.js
alphaui/templates/cdn/assets/index.0835ed98.js
alphaui/templates/cdn/assets/index.0a2ea090.js
alphaui/templates/cdn/assets/index.19bb94ff.css
alphaui/templates/cdn/assets/index.1bc71315.js
