Metadata-Version: 1.0
Name: alphaui
Version: 3.1.4.1
Summary: Python library for easily interacting with trained machine learning models
Home-page: UNKNOWN
Author: UNKNOWN
Author-email: UNKNOWN
License: Apache License 2.0
Keywords: machine learning,visualization,reproducibility
Platform: UNKNOWN
